{
    "@type": "config.global",
    "dht": {
        "@type": "dht.config.global",
        "k": 6,
        "a": 3,
        "static_nodes": {
            "@type": "dht.nodes",
            "nodes": [
                {"@type":"dht.node","id":{"@type":"pub.ed25519","key":"/vjsQUlD9VRCLUryLE95EjjNZ5wIFnq9z15bQYlBup4="},"addr_list":{"@type":"adnl.addressList","addrs":[{"@type":"adnl.address.udp","ip":-972005626,"port":6302}],"version":1594999205,"reinit_date":1594999205,"priority":0,"expire_at":0},"version":1595232032,"signature":"sM+pxGYrJaQ4Hu3G8HpLmrfuysX7vDgwwTk5UaxZ79R2NEWzww33YKCJkg3Qtq4hyKHmJ8xByzCVamMkQYScDA=="},
                {"@type":"dht.node","id":{"@type":"pub.ed25519","key":"tI/ahmJ2KkAVIquYMnH3iSpCKfbYTjfg+j2yxO0qD1c="},"addr_list":{"@type":"adnl.addressList","addrs":[{"@type":"adnl.address.udp","ip":-730912064,"port":30310}],"version":1594995554,"reinit_date":1594995554,"priority":0,"expire_at":0},"version":1595232009,"signature":"t8mvMZlw6XnuYRHYFZ7Nblo2NLHTDaG3Vp0kxVe1IbEYiwKnbxUkOnq02NrTp/olnHMznQIxHbonBUlxTSTdAg=="},
                {"@type":"dht.node","id":{"@type":"pub.ed25519","key":"FqEPiwvWExq2oTahM5dIwaOMAOxqOoLnF57R9klzBf8="},"addr_list":{"@type":"adnl.addressList","addrs":[{"@type":"adnl.address.udp","ip":861481963,"port":30310}],"version":1594939887,"reinit_date":1594939887,"priority":0,"expire_at":0},"version":1595232024,"signature":"q31G0D5eH5Ay5gzMjy8AGBgnU5WhLwpI6AfaAl8nlHOYe5yfGCeQjhUoiP22jQL4LWrZfb2ke5DK95lWElhHAQ=="},
                {"@type":"dht.node","id":{"@type":"pub.ed25519","key":"XX+J7WEpvdYILbo0Eqnj2ZWRr9xO8QfRT9dBVrNjH5c="},"addr_list":{"@type":"adnl.addressList","addrs":[{"@type":"adnl.address.udp","ip":1608088219,"port":30310}],"version":1594929394,"reinit_date":1594929394,"priority":0,"expire_at":0},"version":1595232029,"signature":"K+VoD64RI/NDpmWdk551QkL1vE0iwtXgD8xtWwkdRAnN7nRdWGbqFsFX9jeCfxSiYufAvluyq58ZepqiVZcZBw=="},
                {"@type":"dht.node","id":{"@type":"pub.ed25519","key":"a//noBkOKYehcRqshCchRwe6BfQJpI0COvmOcQNNwbM="},"addr_list":{"@type":"adnl.addressList","addrs":[{"@type":"adnl.address.udp","ip":1679495397,"port":30310}],"version":1595198114,"reinit_date":1595198114,"priority":0,"expire_at":0},"version":1595232027,"signature":"iWrrwP2IVhidbYjHAaSSkVEhCFYsLsMVbm4yh9z37RHHOZcHOZQ4QJsFR63UVRBLOPo+Dek3eK41UGpVBatRAw=="},
                {"@type":"dht.node","id":{"@type":"pub.ed25519","key":"oJzEcMzVO/8VAWYjutckehOU9wpacvxj2yA2VTFEHgI="},"addr_list":{"@type":"adnl.addressList","addrs":[{"@type":"adnl.address.udp","ip":-1952278933,"port":30310}],"version":1594999108,"reinit_date":1594999108,"priority":0,"expire_at":0},"version":1595232012,"signature":"p/cBHbG2NHCNI06C1BTqgoROFfEs2B6W16t0Bt95lsrtjZWtHtydjDsc0hcvLgdX/yRE5UBA2MxFdpIZ6wBzAw=="},
                {"@type":"dht.node","id":{"@type":"pub.ed25519","key":"l06L950udd1ajOU0+x1WwmGyibiuDFErVdrXuFyyfP0="},"addr_list":{"@type":"adnl.addressList","addrs":[{"@type":"adnl.address.udp","ip":1604651435,"port":30310}],"version":1594932849,"reinit_date":1594932849,"priority":0,"expire_at":0},"version":1595231977,"signature":"NLIKKCTEeHhnEeSYhNTHsZohkx3qR8PYS1ca4ZJYElo9ph/QfZAJecdBPwIHRnqYJPg8jiWbeAQdBA4B32YuBg=="},
                {"@type":"dht.node","id":{"@type":"pub.ed25519","key":"uMTEDeQ/oXr96W27S4z6YvnPbGQP10/lLoFbLzAD6wk="},"addr_list":{"@type":"adnl.addressList","addrs":[{"@type":"adnl.address.udp","ip":1608107633,"port":30310}],"version":1594940880,"reinit_date":1594940880,"priority":0,"expire_at":0},"version":1595232026,"signature":"x8ulHncPiA2sPaJ/ZsUqAaFI/i/7t77O9WvPkucce0F7FaYw/gqxji6zVtcLGpVRNboLVmuYzUNLrFJmitJMAQ=="},
                {"@type":"dht.node","id":{"@type":"pub.ed25519","key":"aHUA0PdGZovpJF3zQ1LWIk6l/wwOQhuKVrm1fzRr9Gk="},"addr_list":{"@type":"adnl.addressList","addrs":[{"@type":"adnl.address.udp","ip":-959649838,"port":1338}],"version":1594979154,"reinit_date":1594979154,"priority":0,"expire_at":0},"version":1595232027,"signature":"dmOiiCBDruCF/4qrxct9Jbrb9rBwgCnIjUpfmwQP3DXtr049cxEV+edesPdwIlzV0wcJXD8YyFMFezNoH/xlAA=="},
                {"@type":"dht.node","id":{"@type":"pub.ed25519","key":"wosGfZfdh01aHhcZOLsP30JX5U3IsoavG/lMOG5AQRI="},"addr_list":{"@type":"adnl.addressList","addrs":[{"@type":"adnl.address.udp","ip":577461097,"port":30310}],"version":1594934231,"reinit_date":1594934231,"priority":0,"expire_at":0},"version":1595232015,"signature":"cySy7xpWyEkUwe4keeem6JWjPuEotnv/PIROSNaeOj4yFOUBxRb/R460AcWLT8vAOtYrUWNi9L8ganS/B+SAAQ=="},
                {"@type":"dht.node","id":{"@type":"pub.ed25519","key":"AXOKV0WsCMe+xOgDgkqv1EU57zF8GCVFCnyZHM2Ztgk="},"addr_list":{"@type":"adnl.addressList","addrs":[{"@type":"adnl.address.udp","ip":-1378558676,"port":30310}],"version":1594934053,"reinit_date":1594934053,"priority":0,"expire_at":0},"version":1595232026,"signature":"DxClMUSqfIaqxK+HmHOVISMxyztsVYEq7e44ccygyKlElXPwfSZ65ILDZFk/SmfTi5MlWjtwWL5aWTq2JnwSBA=="},
                {"@type":"dht.node","id":{"@type":"pub.ed25519","key":"NKyD2MTFTNAkys0FDCoPtc6Mgw88A/3w2rp98VXZkik="},"addr_list":{"@type":"adnl.addressList","addrs":[{"@type":"adnl.address.udp","ip":1760484446,"port":30310}],"version":1594934165,"reinit_date":1594934165,"priority":0,"expire_at":0},"version":1595232030,"signature":"N5fdNxM1ybF/BMG7HNMwjcNTRsZ9iIvlnHavvKdHQOB4g9eyxfGeKXFOAJCKCfaHHp4+bELmhkxXsG+0JrgwAg=="},
                {"@type":"dht.node","id":{"@type":"pub.ed25519","key":"VZsyCog7C/8xDZvIDkinLPzJGvObXg0IM5MD7QS/fyA="},"addr_list":{"@type":"adnl.addressList","addrs":[{"@type":"adnl.address.udp","ip":911338312,"port":30310}],"version":1595198107,"reinit_date":1595198107,"priority":0,"expire_at":0},"version":1595232020,"signature":"NIcopJi4KIQiYiQP9/KeJSkQu0clQ5IiYqLmw9gSC1Sd2JfDaeRsdzgLyKJjdsDwf7Sujn+U6SxuSNe4ubnECw=="},
                {"@type":"dht.node","id":{"@type":"pub.ed25519","key":"77uDl0OVQ3jgLd9rnY9eCFvD007m6GrscoGDfHQ7iUA="},"addr_list":{"@type":"adnl.addressList","addrs":[{"@type":"adnl.address.udp","ip":1608114860,"port":30310}],"version":1594931085,"reinit_date":1594931085,"priority":0,"expire_at":0},"version":1595232025,"signature":"+4QAnBPcya7BLyZTWERK/Xt9pG9pmQhEVDzrV9X2yaVUb36KQvEIYUmYoOma7qRh9sG5QgKC6+C2BgzxhG9CAQ=="},
                {"@type":"dht.node","id":{"@type":"pub.ed25519","key":"bLEz7NkbwCv1cWfDZT/8tn1Sp6txnixpXEyHQH/ipPw="},"addr_list":{"@type":"adnl.addressList","addrs":[{"@type":"adnl.address.udp","ip":-1303404668,"port":30310}],"version":1594995569,"reinit_date":1594995569,"priority":0,"expire_at":0},"version":1595232013,"signature":"thBJ8l3hXMlhB83imTKZ52F0uzGjWmPKR0EgKOO4Sb9UX7rcO1KkyPMuBccXyVDimuF7pgPClGVZ3m5IsOqNBA=="},
                {"@type":"dht.node","id":{"@type":"pub.ed25519","key":"dPOLIJXmj41xHPPo4poc2kZRtpiBpaWqLU4P+CUpXvE="},"addr_list":{"@type":"adnl.addressList","addrs":[{"@type":"adnl.address.udp","ip":-1125951953,"port":30310}],"version":1594929507,"reinit_date":1594929507,"priority":0,"expire_at":0},"version":1595232031,"signature":"mxjc0uNFLnVv1ogrotWCyZgJFMMJddPneg3/JQHhs02tbRBwOqZejCs3uLy65F1SKbMOjW0zHoaM8/x47H8JDw=="},
                {"@type":"dht.node","id":{"@type":"pub.ed25519","key":"FB5a7n+1EhYzjBwbd95zCvd8l8BXnVUgEv9lzfAjI+A="},"addr_list":{"@type":"adnl.addressList","addrs":[{"@type":"adnl.address.udp","ip":-773954173,"port":30310}],"version":1594934170,"reinit_date":1594934170,"priority":0,"expire_at":0},"version":1595232033,"signature":"VguwazaXbIMm/SKU/rqxZgT4q97U/nzdvdFzXzVeQrTjct/CV3VEZ+/QIU85dJ/lAyoyfxrunJIjqiDLRGuOAQ=="},
                {"@type":"dht.node","id":{"@type":"pub.ed25519","key":"Frg2o2kpFcfAiRVtdNT7BKpYGepCxVRCecReV7X9CQk="},"addr_list":{"@type":"adnl.addressList","addrs":[{"@type":"adnl.address.udp","ip":-1952278442,"port":30310}],"version":1594995410,"reinit_date":1594995410,"priority":0,"expire_at":0},"version":1595232018,"signature":"axrjvV50WgujKUIi+gUZHcSREK0UCZU2LPG4eaBq5qvG1dJ6TdweOym8r/w2bl2KeyXrjuDC7qEdBHw1jWN8BA=="},
                {"@type":"dht.node","id":{"@type":"pub.ed25519","key":"/pJlAcg6tiacSf5ntfMP+FK2ajnJteNYFcIr9PDxK9I="},"addr_list":{"@type":"adnl.addressList","addrs":[{"@type":"adnl.address.udp","ip":1836814499,"port":30310}],"version":1595173972,"reinit_date":1595173972,"priority":0,"expire_at":0},"version":1595232025,"signature":"R3wQPxVZhmcSKyQJhGDYh/Vcm+Y65HRll+kaQ3w8dTsgMq5aQl90pOdKTRO/kTOwyQh0uhAWNQeq0ENbIYDBDg=="},
                {"@type":"dht.node","id":{"@type":"pub.ed25519","key":"vAFQw8qgwwCND48IusHXqn1uOH61AlxfAx8OTXir5d0="},"addr_list":{"@type":"adnl.addressList","addrs":[{"@type":"adnl.address.udp","ip":1760484683,"port":30310}],"version":1594934167,"reinit_date":1594934167,"priority":0,"expire_at":0},"version":1595232033,"signature":"IaVaxEBP9aB3CKiLWWXU9pZrsAQtv39k4t9lX0Ot4n3Ayxf7vUPlxP8NV1mwNq1TlFEr9JgHDYNGlczaN+ttBA=="},
                {"@type":"dht.node","id":{"@type":"pub.ed25519","key":"++R0FSCgaF6dXCCEV4lDTC9l5XvPQCFVdSU2Kc1n7E8="},"addr_list":{"@type":"adnl.addressList","addrs":[{"@type":"adnl.address.udp","ip":1760766122,"port":30310}],"version":1594934166,"reinit_date":1594934166,"priority":0,"expire_at":0},"version":1595232027,"signature":"OYdZrrLvWeRx3ZqBPYA4xWOLNvrR8AWggVuc93oaH1fUK+0tK9w6O7ZIfgSj9IhOF310d8H0TJDCJtA9Ta0uCw=="},
                {"@type":"dht.node","id":{"@type":"pub.ed25519","key":"OcS4Vu10g1IwG8UFT9w3iQwBaj26VUnkgkOQb2aLeC4="},"addr_list":{"@type":"adnl.addressList","addrs":[{"@type":"adnl.address.udp","ip":861481763,"port":30310}],"version":1595153088,"reinit_date":1595153088,"priority":0,"expire_at":0},"version":1595232021,"signature":"6+8PyG1uhsp+Y6AuVsQ2IF708HYja/LJ7YCbA1TpmtG/WqDXl45eb9ubSj8vkuTZ4JWV48LkGlBXbkvvDrDGAg=="},
                {"@type":"dht.node","id":{"@type":"pub.ed25519","key":"r32d8rmnHBNW3GrFqIK5ViuyeoUW2EczlEeNSB1V9ik="},"addr_list":{"@type":"adnl.addressList","addrs":[{"@type":"adnl.address.udp","ip":1760766486,"port":30310}],"version":1594934165,"reinit_date":1594934165,"priority":0,"expire_at":0},"version":1595232033,"signature":"F4xf0qcjaiLLK92Gdg3vulh4wIEfka+MM+COl4ji9MU2oQLI5aJPLoMHXd21/tsOdh/kEsAq87/cO3OWfzfiAQ=="},
                {"@type":"dht.node","id":{"@type":"pub.ed25519","key":"MGpOgu7Ym2x5ulu/TJ06U0QEFRpGqPm5CBLIpWjYkxM="},"addr_list":{"@type":"adnl.addressList","addrs":[{"@type":"adnl.address.udp","ip":1760484703,"port":30310}],"version":1594934165,"reinit_date":1594934165,"priority":0,"expire_at":0},"version":1595232030,"signature":"AUHBuwTdd9fhMUipIyrrPLAXFiDu1vS2WTbhj6Yjz0Y4xXy4c/Tc5ippGC2NzJZZfh+t5HfT/SqzjpLDAo86Ag=="},
                {"@type":"dht.node","id":{"@type":"pub.ed25519","key":"fKm6agd91UJ9foTKhz9kafjx/tJmvJNm2f7hjIDybn4="},"addr_list":{"@type":"adnl.addressList","addrs":[{"@type":"adnl.address.udp","ip":757154604,"port":30310}],"version":1594995417,"reinit_date":1594995417,"priority":0,"expire_at":0},"version":1595232029,"signature":"eVHdpYftQ1RIYt0HEYrEHcp8ZFSotrNBwaLmYns2vCKOwq0NQjwEd6Y2xulA1Vu3+y3mR56aF4MsxTbc8fvyDQ=="},
                {"@type":"dht.node","id":{"@type":"pub.ed25519","key":"UUZzTFtqbYy9n3kAP7m9sMMhBib3C5Ash7ozvP9Xzh0="},"addr_list":{"@type":"adnl.addressList","addrs":[{"@type":"adnl.address.udp","ip":1608110032,"port":30310}],"version":1594938145,"reinit_date":1594938145,"priority":0,"expire_at":0},"version":1595232030,"signature":"p9h1+Mz5N8NoFHZOpyoVklwGxF1K7dHujiWPfCWoePO6qRYJ22Swrl9Q7kNGlpy+94mUr2d9WFrFKc6ygKnPCw=="},
                {"@type":"dht.node","id":{"@type":"pub.ed25519","key":"KK7oh9rdxmjFeSrF9ipfPdpAJ15jpRF8cUDpBkY5pH8="},"addr_list":{"@type":"adnl.addressList","addrs":[{"@type":"adnl.address.udp","ip":-1402376547,"port":30310}],"version":1594999114,"reinit_date":1594999114,"priority":0,"expire_at":0},"version":1595232029,"signature":"sw1J3t8z9toD9OKnX0/pyfE17yHkn+lm3gmATMOMEC2icCaIAkLcj5wRmSwZyIu5b0fEiYc0mXZD2oTHFto+Dg=="},
                {"@type":"dht.node","id":{"@type":"pub.ed25519","key":"Ze1PPCec1+xpdvoidoxfIHLu6Z09niQiOFxnxzG53Xc="},"addr_list":{"@type":"adnl.addressList","addrs":[{"@type":"adnl.address.udp","ip":1608109242,"port":30310}],"version":1595083563,"reinit_date":1595083563,"priority":0,"expire_at":0},"version":1595232023,"signature":"zY/6x+C3IvLmx1W80PK3XJuop1/9iTuPtUna2sm7r5Pph/invxyX6tYJFNcOrzCUNlGsuNwtM9n1zwF15EgsBQ=="},
                {"@type":"dht.node","id":{"@type":"pub.ed25519","key":"cT1Gcqdy4bLJro6yPHjDbmHFBVnSBSy8BkXsXOAIiU0="},"addr_list":{"@type":"adnl.addressList","addrs":[{"@type":"adnl.address.udp","ip":911439815,"port":30310}],"version":1595198130,"reinit_date":1595198130,"priority":0,"expire_at":0},"version":1595232015,"signature":"g3dl9E4IGsKZ1Z9PJ8fWi5HBJrbppbkkgg7j6w0PG7OWz8+gYcai5C+28o+3Z/iFcgqRCZvfVpJ6FzG/iVBTDw=="},
                {"@type":"dht.node","id":{"@type":"pub.ed25519","key":"LvdwzVnMllgxiu7IQXnMWGLs8jIGemWu00MsLGCWg6g="},"addr_list":{"@type":"adnl.addressList","addrs":[{"@type":"adnl.address.udp","ip":-948637693,"port":30310}],"version":1594934353,"reinit_date":1594934353,"priority":0,"expire_at":0},"version":1595232024,"signature":"naqtSHaM+xCZk0cpF77JPTH/OP/bXWrQ4786/MbPhObSmBzgGK+fcDdCD7RgAu3LL9Dy3Ae7DKeTbZn5U++XAw=="},
                {"@type":"dht.node","id":{"@type":"pub.ed25519","key":"0s4rejhzO3cXwiL5GhKQivJ1wYVRTUvJ+RuPw0ExWT4="},"addr_list":{"@type":"adnl.addressList","addrs":[{"@type":"adnl.address.udp","ip":-1341585298,"port":30310}],"version":1594938080,"reinit_date":1594938080,"priority":0,"expire_at":0},"version":1595232028,"signature":"hxo+h5DUBvaq0E+8mupGvoiC2pCyGdVFwQhi8qmqHr2tI++Bm8iF7yYQLg5HA28EldbRRjA77/RaaQtoWD5vCQ=="},
                {"@type":"dht.node","id":{"@type":"pub.ed25519","key":"rqlDdyKxHv1zTtOnpj3PiSHyMd9Ni2L4pgTBVrZWAYk="},"addr_list":{"@type":"adnl.addressList","addrs":[{"@type":"adnl.address.udp","ip":1422499969,"port":30310}],"version":1594730376,"reinit_date":1594730376,"priority":0,"expire_at":0},"version":1595232008,"signature":"i8Ywo0jMMY0nEQi2w0LGy88dMtg+sW9m12C3pE3QluySscy/NnIdcJ7DPsEfCG4TKORXHGx7HBSoSOv3WMf/Cw=="},
                {"@type":"dht.node","id":{"@type":"pub.ed25519","key":"lu6CrC4p3Fo2LfGL2BlkAJBx+Fba0ZHyLxhm3kUpzFw="},"addr_list":{"@type":"adnl.addressList","addrs":[{"@type":"adnl.address.udp","ip":870197402,"port":30310}],"version":1595172534,"reinit_date":1595172534,"priority":0,"expire_at":0},"version":1595232016,"signature":"HR+hT0Qp5vtfSU1axOFShDHbtMMvLJkKT4ucg2cRJxi0HiX6+JMOka9qLuS4LHG5zAs0+7T497ULatHVrSvZDQ=="},
                {"@type":"dht.node","id":{"@type":"pub.ed25519","key":"P8T4JwEeqJp+W1bYlbrKOJxBZDUbdQD32Rvw+osLd8U="},"addr_list":{"@type":"adnl.addressList","addrs":[{"@type":"adnl.address.udp","ip":839383050,"port":6302}],"version":1595073052,"reinit_date":1595073052,"priority":0,"expire_at":0},"version":1595231997,"signature":"1rUUcAiVEWOyHZQGnyp/8caSmv2oULDIEOfqYmb485ZGGhM3ZVl8ET9FF9hX+qeOT3MFw3xC2ZladfcmL4jWBQ=="},
                {"@type":"dht.node","id":{"@type":"pub.ed25519","key":"orWQ/s+0n82k406xTGvgoPkhpxl58rruYb+qAdXnsQw="},"addr_list":{"@type":"adnl.addressList","addrs":[{"@type":"adnl.address.udp","ip":65162376,"port":30310}],"version":1595198096,"reinit_date":1595198096,"priority":0,"expire_at":0},"version":1595232009,"signature":"wGSGbNOT6vsGD40kMwq3YlZ9ZS1LZWzgkAUT6kVCtK8H1FyEVCxjbZ5Ua0TMeTlUNiL5WLWfKXeMX+Wp8zh/CQ=="},
                {"@type":"dht.node","id":{"@type":"pub.ed25519","key":"SiaDkxuvGfXCk2jEuKfGXhT+uHjsKTLZsawCrq1rCIY="},"addr_list":{"@type":"adnl.addressList","addrs":[{"@type":"adnl.address.udp","ip":1422497462,"port":30310}],"version":1595004557,"reinit_date":1595004557,"priority":0,"expire_at":0},"version":1595232009,"signature":"U/KMw35v+TCItm0BIq5H5MghC4d6EcoqvHfoJHeDhd9vZQSXeN4u7bTaBtBzmrZINGgzW/Dyrfa5lKJaZbaKCQ=="},
                {"@type":"dht.node","id":{"@type":"pub.ed25519","key":"q4ZKqKeh72Ojt5LScxriXyhtwufCemOXl8mksVz5j9c="},"addr_list":{"@type":"adnl.addressList","addrs":[{"@type":"adnl.address.udp","ip":65729134,"port":30310}],"version":1595198106,"reinit_date":1595198106,"priority":0,"expire_at":0},"version":1595232019,"signature":"wRwHNYL/zY4LUBhhnzIIr3ekXhyYp2pxeO/W622IASKMewqap5aB8NKMAnhY+W8/nKolZY5ChbIaQW4QmcjmBA=="},
                {"@type":"dht.node","id":{"@type":"pub.ed25519","key":"uDEkGR64FyUDtjG5nZhrfpggdoiEv9eiDXKRUDmjSNY="},"addr_list":{"@type":"adnl.addressList","addrs":[{"@type":"adnl.address.udp","ip":-947962258,"port":30310}],"version":1594934165,"reinit_date":1594934165,"priority":0,"expire_at":0},"version":1595232017,"signature":"CORqE+imUEcgea0A9VmOFquoFisB6uhtypQyIZDi0O8D6IiVFegZpWntBhc3rewO5Z0uAGEGZ/wuR0zubPJqAw=="},
                {"@type":"dht.node","id":{"@type":"pub.ed25519","key":"LKGrN21ObYG38z7FtNVFf6R2fYDTK4J7kNWWFuLcYeU="},"addr_list":{"@type":"adnl.addressList","addrs":[{"@type":"adnl.address.udp","ip":1760484874,"port":30310}],"version":1594934167,"reinit_date":1594934167,"priority":0,"expire_at":0},"version":1595232032,"signature":"W4qyUAAnhJwgmuzVk/DC54BZC9zHXZVUxT/MY1We1z/u260quPPn1jCYNysDJF+ZEA78QsNPkqphtZccwY4YAg=="},
                {"@type":"dht.node","id":{"@type":"pub.ed25519","key":"x7xLHfamJ1ZvgfOFVrm9cQ2zk23APTvU5crKR23U5Jw="},"addr_list":{"@type":"adnl.addressList","addrs":[{"@type":"adnl.address.udp","ip":1760484878,"port":30310}],"version":1594934167,"reinit_date":1594934167,"priority":0,"expire_at":0},"version":1595232032,"signature":"z6XslqBi+7wpb940bZ1xiFfozI2OcVPs9+SsIGnjtfZpaxO/UwC9LOTqJDYzfmuy1rZuslxvDCJCKiUfiRb9Dw=="},
                {"@type":"dht.node","id":{"@type":"pub.ed25519","key":"cRp6JiL5K/g9Scx5/GGW6hC8GeG9T2oeJaXLY4lZQFk="},"addr_list":{"@type":"adnl.addressList","addrs":[{"@type":"adnl.address.udp","ip":1608094262,"port":30310}],"version":1594996974,"reinit_date":1594996974,"priority":0,"expire_at":0},"version":1595232007,"signature":"k4eyXUsrL3btEk8rtDIzh/Odw5yhXAZcdmM6zZrUI/QIUyNVWH21GWOMiZBHmylyCnRyfIBLQePUNkuZCdPYBg=="},
                {"@type":"dht.node","id":{"@type":"pub.ed25519","key":"mu94B31/zHZCjDeqr1FO0aoP3uGQSpOXxkR4ENim4IY="},"addr_list":{"@type":"adnl.addressList","addrs":[{"@type":"adnl.address.udp","ip":-1125951963,"port":30310}],"version":1595193041,"reinit_date":1595193041,"priority":0,"expire_at":0},"version":1595231999,"signature":"NEon0viVqcFd+sdQsmADzobgJyQqcDSyozpMIC7qFQ3elp8NhnrPT+9jrXlv0rFDAcewnbjgjwhcEj91Pj/sAw=="},
                {"@type":"dht.node","id":{"@type":"pub.ed25519","key":"ZfIdWUWFwXHQNK8XORKupm6LdB+lbUQg5nzw0vsb/kU="},"addr_list":{"@type":"adnl.addressList","addrs":[{"@type":"adnl.address.udp","ip":586135904,"port":30310}],"version":1595198094,"reinit_date":1595198094,"priority":0,"expire_at":0},"version":1595232014,"signature":"5NarEqmd1QkDGYl2S+Fv4phlzG1sHreZDp5l6kBWFFEVIXEWmVWPtpFu5216kd5ViDVe2h00s1FKVDd+EiZDDg=="},
                {"@type":"dht.node","id":{"@type":"pub.ed25519","key":"/PkjQ6jUiPrT+vMkZEf/JAVYhs4FCx0d4KFBZLgL8XI="},"addr_list":{"@type":"adnl.addressList","addrs":[{"@type":"adnl.address.udp","ip":-1874039024,"port":30310}],"version":1594991562,"reinit_date":1594991562,"priority":0,"expire_at":0},"version":1595231989,"signature":"Xbvyreq1dDDHSgIJHXAvsz1/TpIBzGjPsFfx2+Vo0Ldp7rKDjPnxQr4eSMFBk3aii60bigBH3UtmNA5/gE5IBA=="},
                {"@type":"dht.node","id":{"@type":"pub.ed25519","key":"Uf8In/Nx6MyHGN9j9zcKCvbptflxinGBKsQ6Zp+rJMk="},"addr_list":{"@type":"adnl.addressList","addrs":[{"@type":"adnl.address.udp","ip":1401486732,"port":30310}],"version":1595231881,"reinit_date":1595231881,"priority":0,"expire_at":0},"version":1595232014,"signature":"rnDNzObXE05EXAuCbzxkQWoAe5h27qXDC/BeV+g2ef1n0qJUCXK7KlfyIA/WmiiR6TFLL4zhH1ZqNmaH3E3/Bg=="},
                {"@type":"dht.node","id":{"@type":"pub.ed25519","key":"Ds+tqEpgktHtsIrRFPA561JVZdee38M6cd0I+dezSLY="},"addr_list":{"@type":"adnl.addressList","addrs":[{"@type":"adnl.address.udp","ip":1760484382,"port":30310}],"version":1594934165,"reinit_date":1594934165,"priority":0,"expire_at":0},"version":1595232016,"signature":"k6zbEaQFGLEWbpP9BfJPERDI3M1r6MZ/cayeH2vCAwyejTF+i7JEbonKf5nVLKwC3LAx39JiOMFgq8S2Fx2eCA=="},
                {"@type":"dht.node","id":{"@type":"pub.ed25519","key":"rHH9GHp5zL1dsFgWKpTiV5UNq8pObM9oxjEh0V0+m+g="},"addr_list":{"@type":"adnl.addressList","addrs":[{"@type":"adnl.address.udp","ip":-1952263972,"port":30310}],"version":1594995466,"reinit_date":1594995466,"priority":0,"expire_at":0},"version":1595232012,"signature":"3ZPlH7qPZ0CXvQ+CFLN2c8C5+bThjATt2AOi6a7YASscppYFztlT0k6DNwdYymXMkrPGO0PmsDef9vyKr77MDA=="},
                {"@type":"dht.node","id":{"@type":"pub.ed25519","key":"Ee1DckQzG7oaW4XeYLCxTuhSrGm3CUM0SqJIIds/Nz0="},"addr_list":{"@type":"adnl.addressList","addrs":[{"@type":"adnl.address.udp","ip":-947962458,"port":30310}],"version":1594934165,"reinit_date":1594934165,"priority":0,"expire_at":0},"version":1595232020,"signature":"dqKzvIGPa+KWTO/h9YN1Jd4sgDUJWo2WTImgALuzg5jH5o6aRIuynqNe2t2a/kQWXIzMTs5wNNH8sUDgi9uaAg=="},
                {"@type":"dht.node","id":{"@type":"pub.ed25519","key":"qs9+5GsdoND9S1oI4b9mHLsyZYDX1OJU/RnPhU80StE="},"addr_list":{"@type":"adnl.addressList","addrs":[{"@type":"adnl.address.udp","ip":-1952255063,"port":30310}],"version":1594999117,"reinit_date":1594999117,"priority":0,"expire_at":0},"version":1595232021,"signature":"GCQ4UVagTJCWCvdTizW/C4QnfLhEvGGPCEa7kdG0KjDxNXomimjH1jLoYqf/SDpZZGBBPEjWJNd9HGumTEAWCw=="},
                {"@type":"dht.node","id":{"@type":"pub.ed25519","key":"tt9V+I2tkZDWpY9PKNfX7dvEUt7PxmZ65y8t3YKkcC8="},"addr_list":{"@type":"adnl.addressList","addrs":[{"@type":"adnl.address.udp","ip":1760484875,"port":30310}],"version":1594934165,"reinit_date":1594934165,"priority":0,"expire_at":0},"version":1595232005,"signature":"28CY03N8cUO3HqPFinxILgBPaAC4mlrdIvJrg+XFoLFBzZjMAqo6kbGKlCNDI4i6bUiZxSoPO6ZWGxvC/QwaDA=="},
                {"@type":"dht.node","id":{"@type":"pub.ed25519","key":"VMJ7/vGTF/7k18yG90mMALVDFlhXpkQ8s8rw1W7uT6s="},"addr_list":{"@type":"adnl.addressList","addrs":[{"@type":"adnl.address.udp","ip":1740858579,"port":30310}],"version":1594934165,"reinit_date":1594934165,"priority":0,"expire_at":0},"version":1595231989,"signature":"KSZ53YYxDKSSvLV0KnaulcHj8kHKbrU/EDVmACZvkY8nolqQE0U1sWpXuBAC2qQ1cJyaB5/Y2K7ieExSp7EVDQ=="},
                {"@type":"dht.node","id":{"@type":"pub.ed25519","key":"SYHcUcpG7gI0s3b70V1t6jywO1v/G3PJRhtmHQi+Bbg="},"addr_list":{"@type":"adnl.addressList","addrs":[{"@type":"adnl.address.udp","ip":1757547242,"port":30310}],"version":1594934165,"reinit_date":1594934165,"priority":0,"expire_at":0},"version":1595232007,"signature":"Yf4WwOzdijhVQEWkrwnRdwrvMmH81C7TcWXLtHJHIcRCF5O5AATrw6VegmKCXic35YOFGqJRH4hE/LGnmMI/AQ=="},
                {"@type":"dht.node","id":{"@type":"pub.ed25519","key":"cU7VFjb7lrBLpSy7ZcDD2gYlbrk9AfEIlisPbVPDGw4="},"addr_list":{"@type":"adnl.addressList","addrs":[{"@type":"adnl.address.udp","ip":1760484873,"port":30310}],"version":1594934165,"reinit_date":1594934165,"priority":0,"expire_at":0},"version":1595232023,"signature":"ApVoLkzT+ctId9WWsKxYDs40lUtbOBzN8eJ6lib1d/C3sNDUBW1IbG7Rpr6x7J7A1peLyz7J86Lt0Sj/EuB6Cw=="},
                {"@type":"dht.node","id":{"@type":"pub.ed25519","key":"AZZakLH3Gsr4D5zGNesqYRr3uFOcdcEQqtWCbCIDSYI="},"addr_list":{"@type":"adnl.addressList","addrs":[{"@type":"adnl.address.udp","ip":1757547335,"port":30310}],"version":1594934165,"reinit_date":1594934165,"priority":0,"expire_at":0},"version":1595232020,"signature":"MdoiDWWHoB9W2zn1MN4EC9/VZCiWQzvJeVihBHgss2n9nz34GnwmUB6/67/vPxp7wnVrg4qZuDVsgdf/4cDdCA=="},
                {"@type":"dht.node","id":{"@type":"pub.ed25519","key":"Ho9n2q/zpBjoRoCWf4JNgWBBOPclfdmv9JZ3hNzEwEs="},"addr_list":{"@type":"adnl.addressList","addrs":[{"@type":"adnl.address.udp","ip":-733480391,"port":30310}],"version":1594995508,"reinit_date":1594995508,"priority":0,"expire_at":0},"version":1595232019,"signature":"EozUQuqSYNU3PFCkCwKd0wBEdl/SSZlLE9vS12S+hAGRhZAMv4uW485mUxmpnFDGwEHOkrZRPrYl9YyS+eQzDA=="},
                {"@type":"dht.node","id":{"@type":"pub.ed25519","key":"QDOJvX8ZmpH+MOEjRxP070vO91H55/HU2bF5KmppgIQ="},"addr_list":{"@type":"adnl.addressList","addrs":[{"@type":"adnl.address.udp","ip":-1303396997,"port":30310}],"version":1594999170,"reinit_date":1594999170,"priority":0,"expire_at":0},"version":1595232018,"signature":"aF0Ag4sCaZsv+OhDa/ns/UT6DcIGUgdohoYnlYmCwn/qpi7LDh7suf9UKUlncgAyrKBWIknUZ7/5kRDP2kDuBA=="},
                {"@type":"dht.node","id":{"@type":"pub.ed25519","key":"Fxz5C1yHXAoXdO7vVw2dNgGkRnOdf9+y5PNiEkQYPO8="},"addr_list":{"@type":"adnl.addressList","addrs":[{"@type":"adnl.address.udp","ip":-1952266817,"port":30310}],"version":1594995432,"reinit_date":1594995432,"priority":0,"expire_at":0},"version":1595232012,"signature":"+DKvi+9PAgp1hkosAtcg44WotkvfCuxMn8n5Jax/fpbhhjEr+vHbxAug04ooJ7YZzlNt8aStVRBgDBMtldWUBg=="},
                {"@type":"dht.node","id":{"@type":"pub.ed25519","key":"8jbWPxg7ALBbWktdFl539WKEjjS3G513zedJjatB1QQ="},"addr_list":{"@type":"adnl.addressList","addrs":[{"@type":"adnl.address.udp","ip":65831219,"port":30310}],"version":1595198091,"reinit_date":1595198091,"priority":0,"expire_at":0},"version":1595232012,"signature":"nlzq2cIwAz1wxm7NULBIDip2eAiaKPkQhFJHD3e5RKizOutfDAebq5RV8HIF6+7ZR3mzb0Pr1eLtIKfOiK7KBg=="},
                {"@type":"dht.node","id":{"@type":"pub.ed25519","key":"B7jwT+nfs4t58Va/Erlvk3nFgQM9vY+/5ZnRW65CKzo="},"addr_list":{"@type":"adnl.addressList","addrs":[{"@type":"adnl.address.udp","ip":861632477,"port":30310}],"version":1594945232,"reinit_date":1594945232,"priority":0,"expire_at":0},"version":1595232015,"signature":"0OQhCM+XWX6psaUS1TsJa17m/+4bAwNkd9Admh4MeEyk1Y5jccX2f2rWwkVcAKjsnyg4dcP6HdCq9I2+LMeBAg=="},
                {"@type":"dht.node","id":{"@type":"pub.ed25519","key":"HZS2QA9iyHIl3CnilUSLvsajuXlmzmfP3CCKPr7FaO8="},"addr_list":{"@type":"adnl.addressList","addrs":[{"@type":"adnl.address.udp","ip":65804885,"port":30310}],"version":1595198135,"reinit_date":1595198135,"priority":0,"expire_at":0},"version":1595232021,"signature":"KcAwm68Ke33zZWtcduKiuYMq2yqiRI4d7wdM5xiq2z7xSnJIzwkxSM55kEvj6efvCi/Ekj7MI2RYys3fmyz/DQ=="},
                {"@type":"dht.node","id":{"@type":"pub.ed25519","key":"RVasU/RyYk5+tVaFmEeq4N6TUFUNnJTWLQwTTEGWJBQ="},"addr_list":{"@type":"adnl.addressList","addrs":[{"@type":"adnl.address.udp","ip":1297859127,"port":30310}],"version":1594935347,"reinit_date":1594935347,"priority":0,"expire_at":0},"version":1595232012,"signature":"TPq0Qg5q2e003NxNRWzr1D1NPvPkxW7dcxIggvmibOYAJIjGWX6HbbAqbL0Fv0RMyxiVK9nsXLaxMXafJVqqAg=="},
                {"@type":"dht.node","id":{"@type":"pub.ed25519","key":"3wzdbwVSJUdee/ApshwyK5d74du0JniK6sX/L4g7GAs="},"addr_list":{"@type":"adnl.addressList","addrs":[{"@type":"adnl.address.udp","ip":522961419,"port":30310}],"version":1595156669,"reinit_date":1595156669,"priority":0,"expire_at":0},"version":1595232020,"signature":"m0gxBbMGAWYb1u3ammJfi92qzk+lN8X6ALtltL2I2KBXmEi9IfwpkwJ3rikAGrFkAfkljNF/WTsk2AiN+qv0Ag=="}
            ]
        }
    },
    "validator": {
        "@type": "validator.config.global",
        "zero_state": {
            "workchain": -1,
            "shard": -9223372036854775808,
            "seqno": 0,
            "root_hash": "hC+aCcezOtXW4dBQX+KMPkBBhxOL6fgrZsJv7KwhOGQ=",
            "file_hash": "vAhyeILZ1GCgKQQ+zS1MlbNYxEva2rHkLxIRXhZzreY="
        }
    }
}
